query_csv_using_sql/__init__.py
query_csv_using_sql/query_csv_using_sql_main.py
query_csv_using_sql-0.0.1.dist-info/METADATA
query_csv_using_sql-0.0.1.dist-info/WHEEL
query_csv_using_sql-0.0.1.dist-info/licenses/LICENSE
query_csv_using_sql-0.0.1.dist-info/RECORD
