Metadata-Version: 2.4
Name: query_csv_using_sql
Version: 0.0.1
Summary: SOME DESCRIPTION
Project-URL: Homepage, https://github.com/zlilu246/query_csv_using_sql
Project-URL: Issues, https://github.com/zlliu246/query_csv_using_sql/issues
Author-email: Liu Zuo Lin <zlliu246@gmail.com>
License-File: LICENSE
Classifier: License :: OSI Approved :: MIT License
Classifier: Operating System :: OS Independent
Classifier: Programming Language :: Python :: 3
Requires-Python: >=3.8
Requires-Dist: pandas
